factrainer/catboost/__init__.py
factrainer/catboost/py.typed
factrainer_catboost-0.1.27.dist-info/METADATA
factrainer_catboost-0.1.27.dist-info/WHEEL
factrainer_catboost-0.1.27.dist-info/RECORD
