Metadata-Version: 2.4
Name: factrainer-catboost
Version: 0.1.27
Summary: Add your description here
Author-email: ritsuki1227 <ritsuki1227@gmail.com>
Classifier: Programming Language :: Python :: 3
Classifier: Programming Language :: Python :: 3 :: Only
Classifier: Programming Language :: Python :: 3.12
Classifier: Programming Language :: Python :: 3.13
Requires-Python: >=3.12
Requires-Dist: catboost>=1.2.8
Requires-Dist: factrainer-base
